MANIFEST.in
README.md
setup.py
configs/__init__.py
configs/base_setting.py
configs/dev_setting.py
configs/prod_setting.py
core/__init__.py
core/check_param.py
core/common.py
core/conf.py
core/core.py
core/error.py
core/exceptions.py
core/global_settings.py
core/log.py
core/utils.py
core/zyz_flask.py
zyzFlask.egg-info/PKG-INFO
zyzFlask.egg-info/SOURCES.txt
zyzFlask.egg-info/dependency_links.txt
zyzFlask.egg-info/top_level.txt