Metadata-Version: 1.0
Name: zyzFlask
Version: 0.1.0
Summary: 基于flask封装的web开发包
Home-page: UNKNOWN
Author: Asian.zhang
Author-email: Asian_zhang@163.com
License: GNU Lesser General
Platform: UNKNOWN
